[
  { "tipo": "jugador", "dorsal": 1, "name": "A. Remiro", "fullname": "Álex Remiro", "url_name": "alex_remiro", "pos": "POR", "pais": "Euskal Herria", "pais2": "Nafarroa" },
  { "tipo": "jugador", "dorsal": 2, "name": "Odriozola", "fullname": "Álvaro Odriozola", "url_name": "alvaro_odriozola", "pos": "DEF", "pais": "Euskal Herria", "pais2": "Gipuzkoa" },
  { "tipo": "jugador", "dorsal": 3, "name": "Aihen", "fullname": "Aihen Muñoz", "url_name": "aihen_munoz", "pos": "DEF", "pais": "Euskal Herria", "pais2": "Nafarroa" },
  { "tipo": "jugador", "dorsal": 4, "name": "Zubimendi", "fullname": "Martin Zubimendi", "url_name": "martin_zubimendi", "pos": "MED", "pais": "Euskal Herria", "pais2": "Gipuzkoa" },
  { "tipo": "jugador", "dorsal": 5, "name": "Zubeldia", "fullname": "Igor Zubeldia", "url_name": "igor_zubeldia", "pos": "DEF", "pais": "Euskal Herria", "pais2": "Gipuzkoa" },
  { "tipo": "jugador", "dorsal": 6, "name": "Aritz", "fullname": "Aritz Elustondo", "url_name": "aritz_elustondo", "pos": "DEF", "pais": "Euskal Herria", "pais2": "Gipuzkoa" },
  { "tipo": "jugador", "dorsal": 7, "name": "Barrene", "fullname": "Ander Barrenetxea", "url_name": "ander_barrenetxea", "pos": "DEL", "pais": "Euskal Herria", "pais2": "Gipuzkoa" },
  { "tipo": "jugador", "dorsal": 8, "name": "Zakharyan", "fullname": "Arsen Zakharyan", "url_name": "arsen_zakharyan", "pos": "MED", "pais": "Rusia", "pais2": "Armenia" },
  { "tipo": "jugador", "dorsal": 9, "name": "Óskarsson", "fullname": "Orri Óskarsson", "url_name": "orri_oskarsson", "pos": "DEL", "pais": "Islandia", "pais2": null },
  { "tipo": "jugador", "dorsal": 10, "name": "Oyarzabal", "fullname": "Mikel Oyarzabal", "url_name": "mikel_oyarzabal", "pos": "DEL", "pais": "Euskal Herria", "pais2": "Gipuzkoa" },
  { "tipo": "jugador", "dorsal": 11, "name": "Becker", "fullname": "Sheraldo Becker", "url_name": "sheraldo_becker", "pos": "DEL", "pais": "Surinam", "pais2": "Netherlands" },
  { "tipo": "jugador", "dorsal": 12, "name": "Javi López", "fullname": "Javi López", "url_name": "javi_lopez", "pos": "DEF", "pais": "España", "pais2": null },
  { "tipo": "jugador", "dorsal": 13, "name": "Marrero", "fullname": "Unai Marrero", "url_name": "unai_marrero", "pos": "POR", "pais": "Euskal Herria", "pais2": "Gipuzkoa" },
  { "tipo": "jugador", "dorsal": 14, "name": "Take", "fullname": "Takefusa Kubo", "url_name": "takefusa_kubo", "pos": "DEL", "pais": "Japón", "pais2": null },
  { "tipo": "jugador", "dorsal": 16, "name": "Olasagasti", "fullname": "Jon Ander Olasagasti", "url_name": "jon_ander_olasagasti", "pos": "MED", "pais": "Euskal Herria", "pais2": "Gipuzkoa" },
  { "tipo": "jugador", "dorsal": 17, "name": "Sergio Gómez", "fullname": "Sergio Gómez", "url_name": "sergio_gomez", "pos": "DEL", "pais": "Catalunya", "pais2": null },
  { "tipo": "jugador", "dorsal": 18, "name": "H. Traoré", "fullname": "Hamari Traoré", "url_name": "hamari_traore", "pos": "DEF", "pais": "Mali", "pais2": null },
  { "tipo": "jugador", "dorsal": 19, "name": "Aramburu", "fullname": "Jon Mikel Aramburu", "url_name": "jon_mikel_aramburu", "pos": "DEF", "pais": "Venezuela", "pais2": "Euskal Herria" },
  { "tipo": "jugador", "dorsal": 20, "name": "Pacheco", "fullname": "Jon Pacheco", "url_name": "jon_pacheco", "pos": "DEF", "pais": "Euskal Herria", "pais2": "Nafarroa" },
  { "tipo": "jugador", "dorsal": 21, "name": "N. Aguerd", "fullname": "Nayef Aguerd", "url_name": "nayef_aguerd", "pos": "DEF", "pais": "Marruecos", "pais2": null },
  { "tipo": "jugador", "dorsal": 22, "name": "Turrientes", "fullname": "Beñat Turrientes", "url_name": "benat_turrientes", "pos": "MED", "pais": "Euskal Herria", "pais2": "Gipuzkoa" },
  { "tipo": "jugador", "dorsal": 23, "name": "Brais Méndez", "fullname": "Brais Méndez", "url_name": "brais_mendez", "pos": "MED", "pais": "Galicia", "pais2": null },
  { "tipo": "jugador", "dorsal": 24, "name": "Sučić", "fullname": "Luka Sučić", "url_name": "luka_sucic", "pos": "MED", "pais": "Croacia", "pais2": "Austria" },
  { "tipo": "jugador", "dorsal": 28, "name": "Marín", "fullname": "Pablo Marín", "url_name": "pablo_marin", "pos": "MED", "pais": "España", "pais2": null },
  { "tipo": "jugador", "dorsal": 31, "name": "Jon Martín", "fullname": "Jon Martín", "url_name": "jon_martin", "pos": "DEF", "pais": "Euskal Herria", "pais2": "Gipuzkoa" },
  { "tipo": "jugador", "dorsal": 37, "name": "Beitia", "fullname": "Luken Beitia", "url_name": "luken_beitia", "pos": "DEF", "pais": "Euskal Herria", "pais2": "Gipuzkoa" },
  { "tipo": "jugador", "dorsal": 40, "name": "Mariezkurrena", "fullname": "Arkaitz Mariezkurrena", "url_name": "arkaitz_mariezkurrena", "pos": "DEL", "pais": "Euskal Herria", "pais2": "Gipuzkoa" },
  { "tipo": "jugador", "dorsal": 43, "name": "Díaz", "fullname": "Dani Díaz", "url_name": "dani_diaz", "pos": "DEL", "pais": "España", "pais2": null },

  { "tipo": "entrenador", "name": "Imanol", "fullname": "Imanol Alguacil", "url_name": "imanol_alguacil", "pais": "Euskal Herria", "pais2": "Gipuzkoa", "rol": { "es": "1.º entrenador", "eu": "1. entrenatzailea" } },
  { "tipo": "entrenador", "name": "Labaka", "fullname": "Mikel Labaka", "url_name": "mikel_labaka", "pais": "Euskal Herria", "pais2": "Gipuzkoa", "rol": { "es": "2.º entrenador", "eu": "2. entrenatzailea" } },

  { "tipo": "salida", "name": "Urko", "fullname": "Urko González de Zarate", "status": { "es": "Cedido", "eu": "Utzita" }, "url_name": "urko_gonzalez_de_zarate", "pais": "Euskal Herria", "pais2": "Araba" },
  { "tipo": "salida", "name": "Sadiq", "fullname": "Sadiq Umar", "status": { "es": "Cedido", "eu": "Utzita" }, "url_name": "sadiq_umar", "pais": "Nigeria", "pais2": null },
  { "tipo": "salida", "name": "Magunazelaia", "fullname": "Jon Magunazelaia", "status": { "es": "Cedido", "eu": "Utzita" }, "url_name": "jon_magunazelaia", "pais": "Euskal Herria", "pais2": "Gipuzkoa" },
  { "tipo": "salida", "name": "Gorrotxa", "fullname": "Jon Gorrotxategi", "url_name": "jon_gorrotxategi", "status": { "es": "Cedido", "eu": "Utzita" }, "pais": "Euskal Herria", "pais2": "Gipuzkoa" },
  { "tipo": "salida", "name": "Karrikaburu", "fullname": "Jon Karrikaburu", "url_name": "jon_karrikaburu", "status": { "es": "Cedido", "eu": "Utzita" }, "pais": "Euskal Herria", "pais2": "Nafarroa" },
  { "tipo": "salida", "name": "Carlos Fdez.", "fullname": "Carlos Fernández", "status": { "es": "Cedido", "eu": "Utzita" }, "url_name": "carlos_fernandez", "pais": "España", "pais2": null },
  { "tipo": "salida", "name": "Le Normand", "fullname": "Robin Le Normand", "url_name": "robin_le_normand", "status": { "es": "Transferido", "eu": "Salduta" }, "pais": "Brittany", "pais2": "España" },
  { "tipo": "salida", "name": "Merino", "fullname": "Mikel Merino", "url_name": "mikel_merino", "status": { "es": "Transferido", "eu": "Salduta" }, "pais": "Euskal Herria", "pais2": "Nafarroa" },
  { "tipo": "salida", "name": "Rico", "fullname": "Diego Rico", "url_name": "diego_rico", "status": { "es": "Transferido", "eu": "Salduta" }, "pais": "España", "pais2": null },
  { "tipo": "salida", "name": "Sola", "fullname": "Alex Sola", "url_name": "alex_sola", "status": { "es": "Transferido", "eu": "Salduta" }, "pais": "Euskal Herria", "pais2": "Gipuzkoa" },
  { "tipo": "salida", "name": "Navarro", "fullname": "Robert Navarro", "url_name": "robert_navarro", "status": { "es": "Transferido", "eu": "Salduta" }, "pais": "Catalunya", "pais2": "Euskal Herria" },
  { "tipo": "salida", "name": "Merquelanz", "fullname": "Martin Merquelanz", "url_name": "martin_merquelanz", "status": { "es": "Fin de contrato", "eu": "Kontratu amaiera" }, "pais": "Euskal Herria", "pais2": "Gipuzkoa" },
  { "tipo": "salida", "name": "R. López", "fullname": "Roberto López", "url_name": "roberto_lopez", "status": { "es": "Fin de contrato", "eu": "Kontratu amaiera" }, "pais": "España", "pais2": null },
  { "tipo": "salida", "name": "Tierney", "fullname": "Kieran Tierney", "status": { "es": "Fin de cesión", "eu": "Lagapenaren amaiera" }, "url_name": "kieran_tierney", "pais": "Escocia", "pais2": "IslMan" },
  { "tipo": "salida", "name": "Javi Galán", "fullname": "Javi Galán", "status": { "es": "Fin de cesión", "eu": "Lagapenaren amaiera" }, "url_name": "javi_galan", "pais": "España", "pais2": null },
  { "tipo": "salida", "name": "André Silva", "fullname": "André Silva", "status": { "es": "Fin de cesión", "eu": "Lagapenaren amaiera" }, "url_name": "andre_silva", "pais": "Portugal", "pais2": null }
]